cif2cell/ESPInterfaces.py
cif2cell/__init__.py
cif2cell/elementdata.py
cif2cell/spacegroupdata.py
cif2cell/uctools.py
cif2cell/utils.py
cif2cell-2.1.0.data/data/lib/cif2cell/LICENSE
cif2cell-2.1.0.data/data/lib/cif2cell/docs/cif2cell.pdf
cif2cell-2.1.0.data/data/lib/cif2cell/sample_cifs/BaTiO3_cubic.cif
cif2cell-2.1.0.data/data/lib/cif2cell/sample_cifs/BaTiO3_orthorhombic.cif
cif2cell-2.1.0.data/data/lib/cif2cell/sample_cifs/FeAs.cif
cif2cell-2.1.0.data/data/lib/cif2cell/sample_cifs/LSMO.cif
cif2cell-2.1.0.data/data/lib/cif2cell/sample_cifs/Ni20Mn3P6.cif
cif2cell-2.1.0.data/data/lib/cif2cell/sample_cifs/Si.cif
cif2cell-2.1.0.data/data/lib/cif2cell/sample_cifs/Si2Ti.cif
cif2cell-2.1.0.data/data/lib/cif2cell/sample_cifs/SiC.cif
cif2cell-2.1.0.data/data/lib/cif2cell/sample_cifs/alpha-Mn.cif
cif2cell-2.1.0.data/data/lib/cif2cell/sample_cifs/anatase.cif
cif2cell-2.1.0.data/data/lib/cif2cell/sample_cifs/b-Pu.cif
cif2cell-2.1.0.data/data/lib/cif2cell/sample_cifs/gamma-Pu.cif
cif2cell-2.1.0.data/data/lib/cif2cell/sample_cifs/periodic_table/Ac.cif
cif2cell-2.1.0.data/data/lib/cif2cell/sample_cifs/periodic_table/Ag.cif
cif2cell-2.1.0.data/data/lib/cif2cell/sample_cifs/periodic_table/Al.cif
cif2cell-2.1.0.data/data/lib/cif2cell/sample_cifs/periodic_table/Am.cif
cif2cell-2.1.0.data/data/lib/cif2cell/sample_cifs/periodic_table/As.cif
cif2cell-2.1.0.data/data/lib/cif2cell/sample_cifs/periodic_table/Au.cif
cif2cell-2.1.0.data/data/lib/cif2cell/sample_cifs/periodic_table/B.cif
cif2cell-2.1.0.data/data/lib/cif2cell/sample_cifs/periodic_table/Ba.cif
cif2cell-2.1.0.data/data/lib/cif2cell/sample_cifs/periodic_table/Be.cif
cif2cell-2.1.0.data/data/lib/cif2cell/sample_cifs/periodic_table/Bi.cif
cif2cell-2.1.0.data/data/lib/cif2cell/sample_cifs/periodic_table/Bk.cif
cif2cell-2.1.0.data/data/lib/cif2cell/sample_cifs/periodic_table/Br.cif
cif2cell-2.1.0.data/data/lib/cif2cell/sample_cifs/periodic_table/C.cif
cif2cell-2.1.0.data/data/lib/cif2cell/sample_cifs/periodic_table/Ca.cif
cif2cell-2.1.0.dist-info/LICENSE
cif2cell-2.1.0.dist-info/METADATA
cif2cell-2.1.0.dist-info/WHEEL
cif2cell-2.1.0.dist-info/top_level.txt
cif2cell-2.1.0.dist-info/RECORD
