Metadata-Version: 2.1
Name: cif2cell
Version: 2.1.0
Summary: Construct a unit cell from CIF data
Home-page: http://cif2cell.sourceforge.net/
Author: Torbjorn Bjorkman
Author-email: torbjornb@gmail.com
License: GNU General Public License version 3
Classifier: License :: OSI Approved :: GNU General Public License v3 (GPLv3)
Classifier: Operating System :: POSIX :: Linux
Classifier: Operating System :: MacOS :: MacOS X
Classifier: Operating System :: Microsoft :: Windows
Classifier: Programming Language :: Python
Classifier: Programming Language :: Python :: 3.7
Classifier: Programming Language :: Python :: 3.8
Classifier: Programming Language :: Python :: 3.9
Classifier: Programming Language :: Python :: 3.10
Classifier: Programming Language :: Python :: 3.11
Classifier: Topic :: Scientific/Engineering
Requires-Python: >=3.6
License-File: LICENSE
Requires-Dist: PyCifRW ~=4.4.0
Provides-Extra: tests
Requires-Dist: pytest ; extra == 'tests'
